vim_power/__init__.py
vim_power/segments.py
vim_power-1.0.0.dev1.dist-info/DESCRIPTION.rst
vim_power-1.0.0.dev1.dist-info/METADATA
vim_power-1.0.0.dev1.dist-info/metadata.json
vim_power-1.0.0.dev1.dist-info/pbr.json
vim_power-1.0.0.dev1.dist-info/RECORD
vim_power-1.0.0.dev1.dist-info/top_level.txt
vim_power-1.0.0.dev1.dist-info/WHEEL
