Metadata-Version: 2.0
Name: vim-power
Version: 1.0.0.dev1
Summary: Add a `vim` indicator on your shell's Powerline if you stepped in from vim via `:sh`
Home-page: https://github.com/bezhermoso/vim-power
Author: Bez Hermoso
Author-email: bezalelhermoso@gmail.com
License: MIT
Keywords: powerline vim shell
Platform: UNKNOWN
Classifier: Development Status :: 2 - Pre-Alpha
Classifier: Intended Audience :: Developers
Requires-Dist: powerline-status
